linear_power_flow/__init__.py
linear_power_flow/common_interface/__init__.py
linear_power_flow/common_interface/main_interface.py
linear_power_flow/examples/__init__.py
linear_power_flow/examples/pypwr_examples.py
linear_power_flow/rect_model/__init__.py
linear_power_flow/rect_model/load_linearization.py
linear_power_flow/rect_model/lpf_computation.py
linear_power_flow-0.0.2.dist-info/licenses/LICENSE
linear_power_flow-0.0.2.dist-info/METADATA
linear_power_flow-0.0.2.dist-info/WHEEL
linear_power_flow-0.0.2.dist-info/top_level.txt
linear_power_flow-0.0.2.dist-info/RECORD
