Metadata-Version: 2.4
Name: linear-power-flow
Version: 0.0.2
Summary: A Python package for linear power flow analysis in electrical power systems
Home-page: https://github.com/th1275/linear_power_flow
Author: Tianqi Hong
Author-email: Tianqi Hong <tianqi.hong@uga.edu>
License: BSD 3-Clause License
Project-URL: Homepage, https://github.com/th1275/linear_power_flow
Project-URL: Bug Tracker, https://github.com/th1275/linear_power_flow/issues
Project-URL: Documentation, https://github.com/th1275/linear_power_flow#readme
Project-URL: Source Code, https://github.com/th1275/linear_power_flow
Keywords: power flow,linear power flow,power systems,electrical engineering,grid analysis
Classifier: Development Status :: 3 - Alpha
Classifier: Intended Audience :: Science/Research
Classifier: Topic :: Scientific/Engineering :: Mathematics
Classifier: Topic :: Scientific/Engineering :: Physics
Classifier: Programming Language :: Python :: 3
Classifier: Programming Language :: Python :: 3.8
Classifier: Programming Language :: Python :: 3.9
Classifier: Programming Language :: Python :: 3.10
Classifier: Programming Language :: Python :: 3.11
Classifier: Programming Language :: Python :: 3.12
Classifier: Operating System :: OS Independent
Requires-Python: >=3.8
License-File: LICENSE
Requires-Dist: numpy>=1.20.0
Requires-Dist: scipy>=1.7.0
Provides-Extra: dev
Requires-Dist: pytest>=7.0.0; extra == "dev"
Requires-Dist: pytest-cov>=3.0.0; extra == "dev"
Requires-Dist: black>=22.0.0; extra == "dev"
Requires-Dist: flake8>=4.0.0; extra == "dev"
Requires-Dist: mypy>=0.900; extra == "dev"
Requires-Dist: build>=0.7.0; extra == "dev"
Requires-Dist: twine>=4.0.0; extra == "dev"
Provides-Extra: examples
Requires-Dist: pypower>=5.1.0; extra == "examples"
Requires-Dist: pandapower>=2.10.0; extra == "examples"
Requires-Dist: matplotlib>=3.3.0; extra == "examples"
Requires-Dist: plotly>=5.0.0; extra == "examples"
Dynamic: author
Dynamic: home-page
Dynamic: license-file
Dynamic: requires-python
